add_disclaimers/__init__.py
add_disclaimers/api.py
add_disclaimers/application.py
add_disclaimers/get_event.py
add_disclaimers/handler.py
add_disclaimers/sample_events.py
add_disclaimers/controllers/add_disclaimers_controller.py
add_disclaimers/controllers/base_controller.py
add_disclaimers/factories/base_factory.py
add_disclaimers/factories/factory.py
add_disclaimers/infra/aws_request.py
add_disclaimers/infra/rest.py
add_disclaimers/infra/script.py
add_disclaimers/infra/add_disclaimers/add_disclaimers.py
add_disclaimers/models/ad.py
add_disclaimers/models/disclaimer.py
add_disclaimers/models/page.py
add_disclaimers/models/request.py
add_disclaimers/models/response.py
add_disclaimers/models/saved_file.py
add_disclaimers/models/video.py
add_disclaimers/services/add_disclaimers_service.py
add_disclaimers/services/base_service.py
add_disclaimers/utils/file.py
add_disclaimers/utils/helpers.py
add_disclaimers/utils/html.py
add_disclaimers/utils/json.py
add_disclaimers/utils/lambda_helpers.py
add_disclaimers/utils/markdown.py
add_disclaimers/utils/service_helper.py
add_disclaimers/utils/string_utils.py
add_disclaimers/utils/text.py
add_disclaimers/utils/time.py
add_disclaimers/utils/url.py
add_disclaimers/utils/video.py
video_bot_add_disclaimers-0.0.1.dist-info/LICENSE
video_bot_add_disclaimers-0.0.1.dist-info/METADATA
video_bot_add_disclaimers-0.0.1.dist-info/WHEEL
video_bot_add_disclaimers-0.0.1.dist-info/top_level.txt
video_bot_add_disclaimers-0.0.1.dist-info/RECORD
